{
  "name": "Submission Queue",
  "docstatus": 0,
  "idx": 0,
  "read_only": 0,
  "in_create": 0,
  "protect_attached_files": 0,
  "naming_rule": "Random",
  "autoname": "hash",
  "allow_rename": 0,
  "module": "Core",
  "is_submittable": 0,
  "istable": 0,
  "issingle": 0,
  "is_tree": 0,
  "is_calendar_and_gantt": 0,
  "editable_grid": 1,
  "quick_entry": 0,
  "grid_page_length": 0,
  "rows_threshold_for_grid_search": 0,
  "track_changes": 0,
  "track_seen": 0,
  "track_views": 0,
  "custom": 0,
  "beta": 1,
  "is_virtual": 0,
  "queue_in_background": 0,
  "max_attachments": 0,
  "hide_toolbar": 0,
  "allow_copy": 0,
  "allow_import": 0,
  "allow_events_in_timeline": 0,
  "allow_auto_repeat": 0,
  "make_attachments_public": 0,
  "show_title_field_in_link": 0,
  "translated_doctype": 0,
  "sort_field": "creation",
  "sort_order": "DESC",
  "force_re_route_to_default_view": 0,
  "show_preview_popup": 0,
  "show_name_in_global_search": 0,
  "email_append_to": 0,
  "has_web_view": 0,
  "allow_guest_to_view": 0,
  "index_web_pages_for_search": 1,
  "engine": "InnoDB",
  "migration_hash": "b8ff57a5ae5e79a0c13cc6104e591ce6",
  "row_format": "Dynamic",
  "doctype": "DocType",
  "fields": [
    {
      "name": "2p75iaq0s2",
      "docstatus": 0,
      "idx": 1,
      "label": "Status",
      "fieldtype": "Select",
      "fieldname": "status",
      "length": 0,
      "non_negative": 0,
      "hide_days": 0,
      "hide_seconds": 0,
      "reqd": 0,
      "is_virtual": 0,
      "search_index": 0,
      "not_nullable": 0,
      "options": "Queued\nFinished\nFailed",
      "sort_options": 0,
      "show_dashboard": 0,
      "fetch_if_empty": 0,
      "hidden": 1,
      "show_on_timeline": 0,
      "bold": 0,
      "allow_in_quick_entry": 0,
      "translatable": 0,
      "print_hide": 0,
      "print_hide_if_no_value": 0,
      "report_hide": 0,
      "collapsible": 0,
      "hide_border": 0,
      "in_list_view": 1,
      "in_standard_filter": 0,
      "in_preview": 0,
      "sticky": 0,
      "in_filter": 0,
      "in_global_search": 0,
      "read_only": 1,
      "allow_on_submit": 0,
      "ignore_user_permissions": 0,
      "allow_bulk_edit": 0,
      "make_attachment_public": 0,
      "permlevel": 0,
      "ignore_xss_filter": 0,
      "unique": 0,
      "no_copy": 0,
      "set_only_once": 0,
      "remember_last_selected_value": 0,
      "columns": 0,
      "parent": "Submission Queue",
      "parentfield": "fields",
      "parenttype": "DocType",
      "doctype": "DocField"
    },
    {
      "name": "2p75iqlhrh",
      "docstatus": 0,
      "idx": 2,
      "label": "Created At",
      "fieldtype": "Datetime",
      "fieldname": "created_at",
      "length": 0,
      "non_negative": 0,
      "hide_days": 0,
      "hide_seconds": 0,
      "reqd": 0,
      "is_virtual": 1,
      "search_index": 0,
      "not_nullable": 0,
      "sort_options": 0,
      "show_dashboard": 0,
      "fetch_if_empty": 0,
      "hidden": 0,
      "show_on_timeline": 0,
      "bold": 0,
      "allow_in_quick_entry": 0,
      "translatable": 0,
      "print_hide": 0,
      "print_hide_if_no_value": 0,
      "report_hide": 0,
      "collapsible": 0,
      "hide_border": 0,
      "in_list_view": 0,
      "in_standard_filter": 0,
      "in_preview": 0,
      "sticky": 0,
      "in_filter": 0,
      "in_global_search": 0,
      "read_only": 1,
      "allow_on_submit": 0,
      "ignore_user_permissions": 0,
      "allow_bulk_edit": 0,
      "make_attachment_public": 0,
      "permlevel": 0,
      "ignore_xss_filter": 0,
      "unique": 0,
      "no_copy": 0,
      "set_only_once": 0,
      "remember_last_selected_value": 0,
      "columns": 0,
      "parent": "Submission Queue",
      "parentfield": "fields",
      "parenttype": "DocType",
      "doctype": "DocField"
    },
    {
      "name": "2p72hakcis",
      "docstatus": 0,
      "idx": 3,
      "label": "Enqueued By",
      "fieldtype": "Data",
      "fieldname": "enqueued_by",
      "length": 0,
      "non_negative": 0,
      "hide_days": 0,
      "hide_seconds": 0,
      "reqd": 0,
      "is_virtual": 1,
      "search_index": 0,
      "not_nullable": 0,
      "sort_options": 0,
      "show_dashboard": 0,
      "fetch_if_empty": 0,
      "hidden": 0,
      "show_on_timeline": 0,
      "bold": 0,
      "allow_in_quick_entry": 0,
      "translatable": 0,
      "print_hide": 0,
      "print_hide_if_no_value": 0,
      "report_hide": 0,
      "collapsible": 0,
      "hide_border": 0,
      "in_list_view": 0,
      "in_standard_filter": 0,
      "in_preview": 0,
      "sticky": 0,
      "in_filter": 0,
      "in_global_search": 0,
      "read_only": 1,
      "allow_on_submit": 0,
      "ignore_user_permissions": 0,
      "allow_bulk_edit": 0,
      "make_attachment_public": 0,
      "permlevel": 0,
      "ignore_xss_filter": 0,
      "unique": 0,
      "no_copy": 0,
      "set_only_once": 0,
      "remember_last_selected_value": 0,
      "columns": 0,
      "parent": "Submission Queue",
      "parentfield": "fields",
      "parenttype": "DocType",
      "doctype": "DocField"
    },
    {
      "name": "2p7svva7at",
      "docstatus": 0,
      "idx": 4,
      "label": "Job Id",
      "fieldtype": "Link",
      "fieldname": "job_id",
      "length": 0,
      "non_negative": 0,
      "hide_days": 0,
      "hide_seconds": 0,
      "reqd": 0,
      "is_virtual": 0,
      "search_index": 0,
      "not_nullable": 0,
      "options": "RQ Job",
      "sort_options": 0,
      "show_dashboard": 0,
      "fetch_if_empty": 0,
      "hidden": 0,
      "show_on_timeline": 0,
      "bold": 0,
      "allow_in_quick_entry": 0,
      "translatable": 0,
      "print_hide": 0,
      "print_hide_if_no_value": 0,
      "report_hide": 0,
      "collapsible": 0,
      "hide_border": 0,
      "in_list_view": 0,
      "in_standard_filter": 0,
      "in_preview": 0,
      "sticky": 0,
      "in_filter": 0,
      "in_global_search": 0,
      "read_only": 1,
      "allow_on_submit": 0,
      "ignore_user_permissions": 0,
      "allow_bulk_edit": 0,
      "make_attachment_public": 0,
      "permlevel": 0,
      "ignore_xss_filter": 0,
      "unique": 0,
      "no_copy": 0,
      "set_only_once": 0,
      "remember_last_selected_value": 0,
      "columns": 0,
      "parent": "Submission Queue",
      "parentfield": "fields",
      "parenttype": "DocType",
      "doctype": "DocField"
    },
    {
      "name": "2p7880grgh",
      "docstatus": 0,
      "idx": 5,
      "fieldtype": "Column Break",
      "fieldname": "column_break_5",
      "length": 0,
      "non_negative": 0,
      "hide_days": 0,
      "hide_seconds": 0,
      "reqd": 0,
      "is_virtual": 0,
      "search_index": 0,
      "not_nullable": 0,
      "sort_options": 0,
      "show_dashboard": 0,
      "fetch_if_empty": 0,
      "hidden": 0,
      "show_on_timeline": 0,
      "bold": 0,
      "allow_in_quick_entry": 0,
      "translatable": 0,
      "print_hide": 0,
      "print_hide_if_no_value": 0,
      "report_hide": 0,
      "collapsible": 0,
      "hide_border": 0,
      "in_list_view": 0,
      "in_standard_filter": 0,
      "in_preview": 0,
      "sticky": 0,
      "in_filter": 0,
      "in_global_search": 0,
      "read_only": 0,
      "allow_on_submit": 0,
      "ignore_user_permissions": 0,
      "allow_bulk_edit": 0,
      "make_attachment_public": 0,
      "permlevel": 0,
      "ignore_xss_filter": 0,
      "unique": 0,
      "no_copy": 0,
      "set_only_once": 0,
      "remember_last_selected_value": 0,
      "columns": 0,
      "parent": "Submission Queue",
      "parentfield": "fields",
      "parenttype": "DocType",
      "doctype": "DocField"
    },
    {
      "name": "2p7v118k3m",
      "docstatus": 0,
      "idx": 6,
      "label": "Ended At",
      "fieldtype": "Datetime",
      "fieldname": "ended_at",
      "length": 0,
      "non_negative": 0,
      "hide_days": 0,
      "hide_seconds": 0,
      "reqd": 0,
      "is_virtual": 0,
      "search_index": 0,
      "not_nullable": 0,
      "sort_options": 0,
      "show_dashboard": 0,
      "fetch_if_empty": 0,
      "hidden": 0,
      "show_on_timeline": 0,
      "bold": 0,
      "allow_in_quick_entry": 0,
      "translatable": 0,
      "print_hide": 0,
      "print_hide_if_no_value": 0,
      "report_hide": 0,
      "collapsible": 0,
      "hide_border": 0,
      "in_list_view": 0,
      "in_standard_filter": 0,
      "in_preview": 0,
      "sticky": 0,
      "in_filter": 0,
      "in_global_search": 0,
      "read_only": 1,
      "allow_on_submit": 0,
      "ignore_user_permissions": 0,
      "allow_bulk_edit": 0,
      "make_attachment_public": 0,
      "permlevel": 0,
      "ignore_xss_filter": 0,
      "unique": 0,
      "no_copy": 0,
      "set_only_once": 0,
      "remember_last_selected_value": 0,
      "columns": 0,
      "parent": "Submission Queue",
      "parentfield": "fields",
      "parenttype": "DocType",
      "doctype": "DocField"
    },
    {
      "name": "2p7l916r10",
      "docstatus": 0,
      "idx": 7,
      "label": "Reference DocType",
      "fieldtype": "Link",
      "fieldname": "ref_doctype",
      "length": 0,
      "non_negative": 0,
      "hide_days": 0,
      "hide_seconds": 0,
      "reqd": 0,
      "is_virtual": 0,
      "search_index": 0,
      "not_nullable": 0,
      "options": "DocType",
      "sort_options": 0,
      "show_dashboard": 0,
      "fetch_if_empty": 0,
      "hidden": 0,
      "show_on_timeline": 0,
      "bold": 0,
      "allow_in_quick_entry": 0,
      "translatable": 0,
      "print_hide": 0,
      "print_hide_if_no_value": 0,
      "report_hide": 0,
      "collapsible": 0,
      "hide_border": 0,
      "in_list_view": 1,
      "in_standard_filter": 0,
      "in_preview": 0,
      "sticky": 0,
      "in_filter": 0,
      "in_global_search": 0,
      "read_only": 1,
      "allow_on_submit": 0,
      "ignore_user_permissions": 0,
      "allow_bulk_edit": 0,
      "make_attachment_public": 0,
      "permlevel": 0,
      "ignore_xss_filter": 0,
      "unique": 0,
      "no_copy": 0,
      "set_only_once": 0,
      "remember_last_selected_value": 0,
      "columns": 0,
      "parent": "Submission Queue",
      "parentfield": "fields",
      "parenttype": "DocType",
      "doctype": "DocField"
    },
    {
      "name": "2p7kkq7ksa",
      "docstatus": 0,
      "idx": 8,
      "label": "Reference Docname",
      "fieldtype": "Dynamic Link",
      "fieldname": "ref_docname",
      "length": 0,
      "non_negative": 0,
      "hide_days": 0,
      "hide_seconds": 0,
      "reqd": 0,
      "is_virtual": 0,
      "search_index": 1,
      "not_nullable": 0,
      "options": "ref_doctype",
      "sort_options": 0,
      "show_dashboard": 0,
      "fetch_if_empty": 0,
      "hidden": 0,
      "show_on_timeline": 0,
      "bold": 0,
      "allow_in_quick_entry": 0,
      "translatable": 0,
      "print_hide": 0,
      "print_hide_if_no_value": 0,
      "report_hide": 0,
      "collapsible": 0,
      "hide_border": 0,
      "in_list_view": 1,
      "in_standard_filter": 0,
      "in_preview": 0,
      "sticky": 0,
      "in_filter": 0,
      "in_global_search": 0,
      "read_only": 1,
      "allow_on_submit": 0,
      "ignore_user_permissions": 0,
      "allow_bulk_edit": 0,
      "make_attachment_public": 0,
      "permlevel": 0,
      "ignore_xss_filter": 0,
      "unique": 0,
      "no_copy": 0,
      "set_only_once": 0,
      "remember_last_selected_value": 0,
      "columns": 0,
      "parent": "Submission Queue",
      "parentfield": "fields",
      "parenttype": "DocType",
      "doctype": "DocField"
    },
    {
      "name": "2p7pbi232d",
      "docstatus": 0,
      "idx": 9,
      "fieldtype": "Section Break",
      "fieldname": "section_break_8",
      "length": 0,
      "non_negative": 0,
      "hide_days": 0,
      "hide_seconds": 0,
      "reqd": 0,
      "is_virtual": 0,
      "search_index": 0,
      "not_nullable": 0,
      "sort_options": 0,
      "show_dashboard": 0,
      "fetch_if_empty": 0,
      "hidden": 0,
      "show_on_timeline": 0,
      "bold": 0,
      "allow_in_quick_entry": 0,
      "translatable": 0,
      "print_hide": 0,
      "print_hide_if_no_value": 0,
      "report_hide": 0,
      "collapsible": 0,
      "hide_border": 0,
      "in_list_view": 0,
      "in_standard_filter": 0,
      "in_preview": 0,
      "sticky": 0,
      "in_filter": 0,
      "in_global_search": 0,
      "read_only": 0,
      "allow_on_submit": 0,
      "ignore_user_permissions": 0,
      "allow_bulk_edit": 0,
      "make_attachment_public": 0,
      "permlevel": 0,
      "ignore_xss_filter": 0,
      "unique": 0,
      "no_copy": 0,
      "set_only_once": 0,
      "remember_last_selected_value": 0,
      "columns": 0,
      "parent": "Submission Queue",
      "parentfield": "fields",
      "parenttype": "DocType",
      "doctype": "DocField"
    },
    {
      "name": "2p7d76cel2",
      "docstatus": 0,
      "idx": 10,
      "label": "Exception",
      "fieldtype": "Long Text",
      "fieldname": "exception",
      "length": 0,
      "non_negative": 0,
      "hide_days": 0,
      "hide_seconds": 0,
      "reqd": 0,
      "is_virtual": 0,
      "search_index": 0,
      "not_nullable": 0,
      "sort_options": 0,
      "show_dashboard": 0,
      "fetch_if_empty": 0,
      "hidden": 0,
      "show_on_timeline": 0,
      "bold": 0,
      "allow_in_quick_entry": 0,
      "translatable": 0,
      "print_hide": 0,
      "print_hide_if_no_value": 0,
      "report_hide": 0,
      "collapsible": 0,
      "hide_border": 0,
      "in_list_view": 0,
      "in_standard_filter": 0,
      "in_preview": 0,
      "sticky": 0,
      "in_filter": 0,
      "in_global_search": 0,
      "read_only": 1,
      "allow_on_submit": 0,
      "ignore_user_permissions": 0,
      "allow_bulk_edit": 0,
      "make_attachment_public": 0,
      "permlevel": 0,
      "ignore_xss_filter": 0,
      "unique": 0,
      "no_copy": 0,
      "set_only_once": 0,
      "remember_last_selected_value": 0,
      "columns": 0,
      "parent": "Submission Queue",
      "parentfield": "fields",
      "parenttype": "DocType",
      "doctype": "DocField"
    }
  ],
  "permissions": [
    {
      "name": "2p7qu6shlp",
      "owner": "Administrator",
      "creation": "2022-10-04 00:41:00.028163",
      "modified": "2025-04-15 16:51:01.565841",
      "modified_by": "Administrator",
      "docstatus": 0,
      "idx": 1,
      "role": "System Manager",
      "if_owner": 0,
      "permlevel": 0,
      "select": 0,
      "read": 1,
      "write": 0,
      "create": 0,
      "delete": 0,
      "submit": 0,
      "cancel": 0,
      "amend": 0,
      "report": 1,
      "export": 1,
      "import": 0,
      "share": 1,
      "print": 1,
      "email": 1,
      "parent": "Submission Queue",
      "parentfield": "permissions",
      "parenttype": "DocType",
      "doctype": "DocPerm"
    },
    {
      "name": "2p7enf3jtq",
      "owner": "Administrator",
      "creation": "2022-10-04 00:41:00.028163",
      "modified": "2025-04-15 16:51:01.565841",
      "modified_by": "Administrator",
      "docstatus": 0,
      "idx": 2,
      "role": "Desk User",
      "if_owner": 1,
      "permlevel": 0,
      "select": 0,
      "read": 1,
      "write": 0,
      "create": 0,
      "delete": 0,
      "submit": 0,
      "cancel": 0,
      "amend": 0,
      "report": 0,
      "export": 0,
      "import": 0,
      "share": 0,
      "print": 0,
      "email": 0,
      "parent": "Submission Queue",
      "parentfield": "permissions",
      "parenttype": "DocType",
      "doctype": "DocPerm"
    }
  ],
  "actions": [],
  "links": [],
  "states": [
    {
      "name": "2p7n7flti7",
      "owner": "Administrator",
      "creation": "2022-10-04 00:41:00.028163",
      "modified": "2025-04-15 16:51:01.565841",
      "modified_by": "Administrator",
      "docstatus": 0,
      "idx": 1,
      "title": "Queued",
      "color": "Blue",
      "custom": 0,
      "parent": "Submission Queue",
      "parentfield": "states",
      "parenttype": "DocType",
      "doctype": "DocType State"
    },
    {
      "name": "2p712cpqks",
      "owner": "Administrator",
      "creation": "2022-10-04 00:41:00.028163",
      "modified": "2025-04-15 16:51:01.565841",
      "modified_by": "Administrator",
      "docstatus": 0,
      "idx": 2,
      "title": "Failed",
      "color": "Red",
      "custom": 0,
      "parent": "Submission Queue",
      "parentfield": "states",
      "parenttype": "DocType",
      "doctype": "DocType State"
    },
    {
      "name": "2p7b6laphl",
      "owner": "Administrator",
      "creation": "2022-10-04 00:41:00.028163",
      "modified": "2025-04-15 16:51:01.565841",
      "modified_by": "Administrator",
      "docstatus": 0,
      "idx": 3,
      "title": "Finished",
      "color": "Green",
      "custom": 0,
      "parent": "Submission Queue",
      "parentfield": "states",
      "parenttype": "DocType",
      "doctype": "DocType State"
    }
  ]
}